DichengbenPaoniu/README.md
DichengbenPaoniu/__init__.py
DichengbenPaoniu/__main__.py
DichengbenPaoniu/file.epub
DichengbenPaoniu/index.html
DichengbenPaoniu/css/__init__.py
DichengbenPaoniu/css/annotations.css
DichengbenPaoniu/css/main.css
DichengbenPaoniu/css/normalize.css
DichengbenPaoniu/css/popup.css
DichengbenPaoniu/font/__init__.py
DichengbenPaoniu/font/fontello.eot
DichengbenPaoniu/font/fontello.svg
DichengbenPaoniu/font/fontello.ttf
DichengbenPaoniu/font/fontello.woff
DichengbenPaoniu/img/__init__.py
DichengbenPaoniu/img/annotator-glyph-sprite.png
DichengbenPaoniu/img/annotator-icon-sprite.png
DichengbenPaoniu/img/apple-touch-icon.png
DichengbenPaoniu/img/cancelfullscreen.png
DichengbenPaoniu/img/close.png
DichengbenPaoniu/img/fullscreen.png
DichengbenPaoniu/img/loader.gif
DichengbenPaoniu/img/menu-icon.png
DichengbenPaoniu/img/save.png
DichengbenPaoniu/img/saved.png
DichengbenPaoniu/img/settings-s.png
DichengbenPaoniu/img/settings.png
DichengbenPaoniu/img/star.png
DichengbenPaoniu/js/__init__.py
DichengbenPaoniu/js/epub.js
DichengbenPaoniu/js/epub.min.js
DichengbenPaoniu/js/epub.min.map
DichengbenPaoniu/js/hooks.min.js
DichengbenPaoniu/js/hooks.min.map
DichengbenPaoniu/js/reader.js
DichengbenPaoniu/js/reader.js.map
DichengbenPaoniu/js/reader.min.js
DichengbenPaoniu/js/reader.min.map
DichengbenPaoniu/js/hooks/__init__.py
DichengbenPaoniu/js/hooks/extensions/__init__.py
DichengbenPaoniu/js/hooks/extensions/highlight.js
DichengbenPaoniu/js/libs/__init__.py
DichengbenPaoniu/js/libs/jquery.min.js
DichengbenPaoniu/js/libs/localforage.min.js
DichengbenPaoniu/js/libs/screenfull.js
DichengbenPaoniu/js/libs/screenfull.min.js
DichengbenPaoniu/js/libs/zip.min.js
DichengbenPaoniu/js/plugins/__init__.py
DichengbenPaoniu/js/plugins/hypothesis.js
DichengbenPaoniu/js/plugins/search.js
dichengben_paoniu-2022.10.11.0.dist-info/METADATA
dichengben_paoniu-2022.10.11.0.dist-info/WHEEL
dichengben_paoniu-2022.10.11.0.dist-info/entry_points.txt
dichengben_paoniu-2022.10.11.0.dist-info/top_level.txt
dichengben_paoniu-2022.10.11.0.dist-info/RECORD
